{
  "environment": "web",
  "format": "html",
  "prefix": "https://storage.googleapis.com",
  "mainga": "UA-49880327-14",
  "updated": "2023-05-14T11:59:06Z",
  "id": "biti-ipm-system-linux-lab",
  "duration": 0,
  "title": "BITI IPM Lab - System Information",
  "authors": "Roland Pellegrini",
  "summary": "BITI IPM Lab - System Information",
  "source": "biti-ipm-system-linux-lab.md",
  "theme": "",
  "status": [
    "draft"
  ],
  "category": [
    "linux"
  ],
  "tags": [
    "biti",
    "introduction",
    "ipm",
    "system"
  ],
  "url": "biti-ipm-system-linux-lab"
}
