{
  "environment": "web",
  "format": "html",
  "prefix": "https://storage.googleapis.com",
  "mainga": "UA-49880327-14",
  "updated": "2024-01-13T07:57:58Z",
  "id": "iac-container-intro",
  "duration": 0,
  "title": "Container Technologies - Lab 1 - Introduction / Setup",
  "authors": "Thomas Schuetz",
  "summary": "Lab 1 - Container Intro (Exoscale Edition)",
  "source": "containers-exo-intro.md",
  "theme": "",
  "status": [
    "published"
  ],
  "category": [
    "containers"
  ],
  "tags": [
    "containers",
    "exoscale",
    "introduction"
  ],
  "url": "iac-container-intro"
}
