{
  "environment": "web",
  "format": "html",
  "prefix": "https://storage.googleapis.com",
  "mainga": "UA-49880327-14",
  "updated": "2021-10-13T21:40:16+02:00",
  "id": "biti-ipm-compute-lab",
  "duration": 0,
  "title": "BITI IPM Lab - Compute",
  "authors": "Roland Pellegrini",
  "summary": "BITI IPM Lab - Compute",
  "source": "biti-ipm-compute-lab.md",
  "theme": "",
  "status": [
    "published"
  ],
  "category": [
    "linux"
  ],
  "tags": [
    "biti",
    "compute",
    "cpu",
    "introduction",
    "ipm"
  ],
  "url": "biti-ipm-compute-lab"
}
